Metadata-Version: 1.1
Name: dash-facebook-login
Version: 0.0.2
Summary: A Facebook Login component for Plotly Dash
Home-page: UNKNOWN
Author: Miklos Danka <danka.miklos@gmail.com>
Author-email: UNKNOWN
License: MIT
Platform: UNKNOWN
Classifier: Framework :: Dash
